mst/__init__.py
mst/mst.py
mst-0.0.1.dist-info/METADATA
mst-0.0.1.dist-info/WHEEL
mst-0.0.1.dist-info/licenses/LICENSE
mst-0.0.1.dist-info/RECORD
